NetkillerLinuxFix1/README.md
NetkillerLinuxFix1/__init__.py
NetkillerLinuxFix1/__main__.py
NetkillerLinuxFix1/file.epub
NetkillerLinuxFix1/index.html
NetkillerLinuxFix1/css/__init__.py
NetkillerLinuxFix1/css/annotations.css
NetkillerLinuxFix1/css/main.css
NetkillerLinuxFix1/css/normalize.css
NetkillerLinuxFix1/css/popup.css
NetkillerLinuxFix1/font/__init__.py
NetkillerLinuxFix1/font/fontello.eot
NetkillerLinuxFix1/font/fontello.svg
NetkillerLinuxFix1/font/fontello.ttf
NetkillerLinuxFix1/font/fontello.woff
NetkillerLinuxFix1/img/__init__.py
NetkillerLinuxFix1/img/annotator-glyph-sprite.png
NetkillerLinuxFix1/img/annotator-icon-sprite.png
NetkillerLinuxFix1/img/apple-touch-icon.png
NetkillerLinuxFix1/img/cancelfullscreen.png
NetkillerLinuxFix1/img/close.png
NetkillerLinuxFix1/img/fullscreen.png
NetkillerLinuxFix1/img/loader.gif
NetkillerLinuxFix1/img/menu-icon.png
NetkillerLinuxFix1/img/save.png
NetkillerLinuxFix1/img/saved.png
NetkillerLinuxFix1/img/settings-s.png
NetkillerLinuxFix1/img/settings.png
NetkillerLinuxFix1/img/star.png
NetkillerLinuxFix1/js/__init__.py
NetkillerLinuxFix1/js/epub.js
NetkillerLinuxFix1/js/epub.min.js
NetkillerLinuxFix1/js/epub.min.map
NetkillerLinuxFix1/js/hooks.min.js
NetkillerLinuxFix1/js/hooks.min.map
NetkillerLinuxFix1/js/reader.js
NetkillerLinuxFix1/js/reader.js.map
NetkillerLinuxFix1/js/reader.min.js
NetkillerLinuxFix1/js/reader.min.map
NetkillerLinuxFix1/js/hooks/__init__.py
NetkillerLinuxFix1/js/hooks/extensions/__init__.py
NetkillerLinuxFix1/js/hooks/extensions/highlight.js
NetkillerLinuxFix1/js/libs/__init__.py
NetkillerLinuxFix1/js/libs/jquery.min.js
NetkillerLinuxFix1/js/libs/localforage.min.js
NetkillerLinuxFix1/js/libs/screenfull.js
NetkillerLinuxFix1/js/libs/screenfull.min.js
NetkillerLinuxFix1/js/libs/zip.min.js
NetkillerLinuxFix1/js/plugins/__init__.py
NetkillerLinuxFix1/js/plugins/hypothesis.js
NetkillerLinuxFix1/js/plugins/search.js
netkiller_linux_fix1-2025.3.24.1.dist-info/METADATA
netkiller_linux_fix1-2025.3.24.1.dist-info/WHEEL
netkiller_linux_fix1-2025.3.24.1.dist-info/entry_points.txt
netkiller_linux_fix1-2025.3.24.1.dist-info/top_level.txt
netkiller_linux_fix1-2025.3.24.1.dist-info/RECORD
